[
 {
  "Status": 0,
  "ResultStr": "exec error: context deadline exceeded, stderr: ",
  "srcNodeName": "paas-cnp-istioipv6-87",
  "dstNodeName": "paas-cnp-istioipv6-87",
  "targetIP": "fd11:1111:1111:234:d041:705d:f4ca:9a5f"
 },
 {
  "Status": 0,
  "ResultStr": "exec error: context deadline exceeded, stderr: ",
  "srcNodeName": "paas-cnp-istioipv6-88",
  "dstNodeName": "paas-cnp-istioipv6-87",
  "targetIP": "fd11:1111:1111:234:d041:705d:f4ca:9a5f"
 },
 {
  "Status": 0,
  "ResultStr": "exec error: context deadline exceeded, stderr: ",
  "srcNodeName": "paas-cnp-istioipv6-84",
  "dstNodeName": "paas-cnp-istioipv6-87",
  "targetIP": "fd11:1111:1111:234:d041:705d:f4ca:9a5f"
 }
]